{
  "pr_number": 1507,
  "title": "update dev",
  "author": "hynek",
  "reason": {
    "description": "",
    "commit_messages": [
      "update dev"
    ]
  },
  "python_diffs": [
    {
      "file": "src/attr/_make.py",
      "patch": "@@ -569,7 +569,7 @@ def _frozen_delattrs(self, name):\n     \"\"\"\n     Attached to frozen classes as __delattr__.\n     \"\"\"\n-    if isinstance(self, BaseException) and name in (\"__notes__\",):\n+    if isinstance(self, BaseException) and name == \"__notes__\":\n         BaseException.__delattr__(self, name)\n         return\n \n@@ -1096,9 +1096,7 @@ def _attach_init(cls_dict, globs):\n         return self\n \n     def add_replace(self):\n-        self._cls_dict[\"__replace__\"] = self._add_method_dunders(\n-            lambda self, **changes: evolve(self, **changes)\n-        )\n+        self._cls_dict[\"__replace__\"] = self._add_method_dunders(evolve)\n         return self\n \n     def add_match_args(self):\n@@ -3087,9 +3085,7 @@ def __init__(self, converter, *, takes_self=False, takes_field=False):\n                 value, field\n             )\n         else:\n-            self.__call__ = lambda value, instance, field: self.converter(\n-                value, instance, field\n-            )\n+            self.__call__ = self.converter\n \n         rt = ex.get_return_type()\n         if rt is not None:\n"
    },
    {
      "file": "tests/test_make.py",
      "patch": "@@ -116,9 +116,7 @@ def v():\n \n         assert v == a._validator\n \n-    @pytest.mark.parametrize(\n-        \"wrap\", [lambda v: v, lambda v: [v], lambda v: and_(v)]\n-    )\n+    @pytest.mark.parametrize(\"wrap\", [lambda v: v, lambda v: [v], and_])\n     def test_validator_decorator(self, wrap):\n         \"\"\"\n         If _CountingAttr.validator is used as a decorator and there is already\n@@ -1775,9 +1773,7 @@ def test_frozen(self):\n         \"\"\"\n         Converters circumvent immutability.\n         \"\"\"\n-        C = make_class(\n-            \"C\", {\"x\": attr.ib(converter=lambda v: int(v))}, frozen=True\n-        )\n+        C = make_class(\"C\", {\"x\": attr.ib(converter=int)}, frozen=True)\n         C(\"1\")\n \n \n"
    }
  ]
}